{
    "KPlugin": {
        "Name": "Custom Header Style", 
        "Name[gl]": "Estilo de cabeceira personalizada", 
        "Name[nl]": "Stijl met aangepast aantal headers", 
        "Name[pt]": "Estilo de Cabeçalho Personalizado", 
        "Name[pt_BR]": "Estilo de cabeçalho Personalizado", 
        "Name[sv]": "Egen rubrikstil", 
        "Name[uk]": "Нетиповий стиль заголовків", 
        "Name[x-test]": "xxCustom Header Stylexx", 
        "ServiceTypes": [
            "MessageViewerHeaderStyle/Plugin"
        ], 
        "Version": "1.0"
    }, 
    "X-KDE-MessageViewer-Header-Order": "3"
}